jenkins_build
